pytest_snap/__init__.py
pytest_snap/__main__.py
pytest_snap/baseline.py
pytest_snap/budgets.py
pytest_snap/cli.py
pytest_snap/config.py
pytest_snap/diff.py
pytest_snap/fingerprint.py
pytest_snap/plugin.py
pytest_snap/py.typed
pytest_snap/render.py
pytest_snapcheck-0.1.5.dist-info/licenses/LICENSE
pytest_snapcheck-0.1.5.dist-info/METADATA
pytest_snapcheck-0.1.5.dist-info/WHEEL
pytest_snapcheck-0.1.5.dist-info/entry_points.txt
pytest_snapcheck-0.1.5.dist-info/top_level.txt
pytest_snapcheck-0.1.5.dist-info/RECORD
