Metadata-Version: 2.4
Name: pytest-snapcheck
Version: 0.1.5
Summary: Minimal deterministic test-run snapshot capture for pytest.
Author: Cyril Rikh
License-Expression: MIT
Project-URL: Homepage, https://github.com/cr5459/pytest-snap
Project-URL: Issues, https://github.com/cr5459/pytest-snap/issues
Keywords: pytest,testing,snapshot,regression
Classifier: Framework :: Pytest
Classifier: Programming Language :: Python :: 3
Classifier: Programming Language :: Python :: 3 :: Only
Classifier: Typing :: Typed
Requires-Python: >=3.9
License-File: LICENSE
Requires-Dist: pytest>=8.0
Provides-Extra: dev
Requires-Dist: pytest>=8.0; extra == "dev"
Requires-Dist: build; extra == "dev"
Requires-Dist: twine; extra == "dev"
Requires-Dist: rich>=13.7; extra == "dev"
Requires-Dist: typer>=0.12; extra == "dev"
Provides-Extra: test
Requires-Dist: pytest>=8.0; extra == "test"
Dynamic: license-file
